Metadata-Version: 2.1
Name: mixto-py
Version: 0.0.1
Summary: UNKNOWN
Home-page: https://github.com/securisec/mixto-py
Author: Hapsida @securisec
License: GPL
Project-URL: Documentation, https://mixto-py.readthedocs.io/en/latest/
Project-URL: Source Code, https://github.com/securisec/mixto-py
Platform: UNKNOWN
Classifier: Programming Language :: Python :: 3.7
Requires-Python: >=3.6
